{
    "app_name": "AgroBridge",
    "home_link": "مرکزی صفحہ",
    "foundation_link": "فاؤنڈیشن",
    "hero_title": "ہماری سرزمین کا وعدہ، دنیا کے لیے سربasta۔",
    "hero_subtitle": "ہر پروڈکٹ اصلیت، معیار اور منصفانہ تجارت کی کہانی بیان کرتا ہے، جو ہمارے ناقابل تغیر لیجر میں تصدیق شدہ ہے۔ اسے دریافت کرنے کے لیے اپنی پیکیجنگ پر QR کوڈ اسکین کریں۔",
    "foundation_title": "اپنے لوگوں سے وابستگی",
    "foundation_description": "AgroBridge ٹیکنالوجی سے بڑھ کر ہے؛ یہ ہماری برادریوں کی ترقی کے لیے ایک پل ہے۔",
    "learn_more_foundation": "فاؤنڈیشن کے بارے میں مزید جانیں",
    "footer_copy": "© 2025 AgroBridge International. جملہ حقوق محفوظ ہیں."
}
